indy_credx/__init__.py
indy_credx/bindings.py
indy_credx/error.py
indy_credx/indy_credx.dll
indy_credx/types.py
indy_credx/version.py
indy_credx-1.1.1.dist-info/METADATA
indy_credx-1.1.1.dist-info/WHEEL
indy_credx-1.1.1.dist-info/top_level.txt
indy_credx-1.1.1.dist-info/RECORD
