Metadata-Version: 2.1
Name: indy-credx
Version: 1.1.1
Summary: UNKNOWN
Home-page: https://github.com/hyperledger/indy-shared-rs
Author: Hyperledger Indy Contributors
Author-email: indy@lists.hyperledger.org
License: UNKNOWN
Platform: UNKNOWN
Classifier: Programming Language :: Python :: 3
Classifier: License :: OSI Approved :: Apache Software License
Classifier: Operating System :: OS Independent
Requires-Python: >=3.6.3
